{
    "soils": [
        {
            "soil_id": "SAB0041243",
            "sl_loc_3": "Pergamino",
            "soil_long": -60.4,
            "smke": "IB001",
            "sldp": "-99",
            "classification": "ARGIUDOL t\u00ef\u00bf\u00bdpico",
            "sscol": "BN",
            "salb": "0.13",
            "sldr": "0.60",
            "slro": "81.0",
            "slpf": "1.00",
            "soil_name": "Dulce",
            "slnf": "1.00",
            "sl_loc_1": "ARGENTINA",
            "slu1": "9.6",
            "smpx": "IB001",
            "soilLayer": [
                {
                    "slni": "-99",
                    "slrgf": "1.00",
                    "sldul": "0.281",
                    "slbdm": "1.10",
                    "slphb": "-99",
                    "slsil": "63.9",
                    "slll": "0.128",
                    "slcly": "20.6",
                    "slcec": "-99",
                    "slcf": "0.0",
                    "sloc": "2.26",
                    "slmh": "AP",
                    "slphw": "6.2",
                    "slsat": "0.508",
                    "sllb": "014"
                },
                {
                    "slni": "-99",
                    "slrgf": "0.82",
                    "sldul": "0.296",
                    "slbdm": "1.13",
                    "slphb": "-99",
                    "slsil": "62.6",
                    "slll": "0.145",
                    "slcly": "24.6",
                    "slcec": "-99",
                    "slcf": "0.0",
                    "sloc": "1.92",
                    "slmh": "A12",
                    "slphw": "6.2",
                    "slsat": "0.496",
                    "sllb": "034"
                },
                {
                    "slni": "-99",
                    "slrgf": "0.10",
                    "sldul": "0.297",
                    "slbdm": "1.22",
                    "slphb": "-99",
                    "slsil": "57.9",
                    "slll": "0.155",
                    "slcly": "26.8",
                    "slcec": "-99",
                    "slcf": "0.0",
                    "sloc": "0.92",
                    "slmh": "A3",
                    "slphw": "6.5",
                    "slsat": "0.465",
                    "sllb": "045"
                },
                {
                    "slni": "-99",
                    "slrgf": "0.04",
                    "sldul": "0.317",
                    "slbdm": "1.26",
                    "slphb": "-99",
                    "slsil": "53.2",
                    "slll": "0.180",
                    "slcly": "32.4",
                    "slcec": "-99",
                    "slcf": "0.0",
                    "sloc": "0.54",
                    "slmh": "B1",
                    "slphw": "6.6",
                    "slsat": "0.450",
                    "sllb": "058"
                },
                {
                    "slni": "-99",
                    "slrgf": "0.04",
                    "sldul": "0.348",
                    "slbdm": "1.27",
                    "slphb": "-99",
                    "slsil": "48.2",
                    "slll": "0.213",
                    "slcly": "39.8",
                    "slcec": "-99",
                    "slcf": "0.0",
                    "sloc": "0.51",
                    "slmh": "B21t",
                    "slphw": "6.7",
                    "slsat": "0.445",
                    "sllb": "075"
                },
                {
                    "slni": "-99",
                    "slrgf": "0.04",
                    "sldul": "0.343",
                    "slbdm": "1.32",
                    "slphb": "-99",
                    "slsil": "46.6",
                    "slll": "0.211",
                    "slcly": "39.4",
                    "slcec": "-99",
                    "slcf": "0.0",
                    "sloc": "0.05",
                    "slmh": "B22t",
                    "slphw": "6.8",
                    "slsat": "0.429",
                    "sllb": "100"
                },
                {
                    "slni": "-99",
                    "slrgf": "0.10",
                    "sldul": "0.281",
                    "slbdm": "1.31",
                    "slphb": "-99",
                    "slsil": "54.1",
                    "slll": "0.145",
                    "slcly": "24.6",
                    "slcec": "-99",
                    "slcf": "0.0",
                    "sloc": "0.05",
                    "slmh": "B3",
                    "slphw": "6.9",
                    "slsat": "0.432",
                    "sllb": "120"
                },
                {
                    "slni": "-99",
                    "slrgf": "0.10",
                    "sldul": "0.281",
                    "slbdm": "1.31",
                    "slphb": "-99",
                    "slsil": "54.1",
                    "slll": "0.145",
                    "slcly": "24.6",
                    "slcec": "-99",
                    "slcf": "0.0",
                    "sloc": "0.05",
                    "slmh": "B3",
                    "slphw": "6.9",
                    "slsat": "0.432",
                    "sllb": "140"
                },
                {
                    "slni": "-99",
                    "slrgf": "0.10",
                    "sldul": "0.260",
                    "slbdm": "1.29",
                    "slphb": "-99",
                    "slsil": "59.4",
                    "slll": "0.122",
                    "slcly": "19.3",
                    "slcec": "-99",
                    "slcf": "0.0",
                    "sloc": "0.05",
                    "slmh": "C",
                    "slphw": "7.0",
                    "slsat": "0.439",
                    "sllb": "180"
                },
                {
                    "slni": "-99",
                    "slrgf": "0.01",
                    "sldul": "0.260",
                    "slbdm": "1.29",
                    "slphb": "-99",
                    "slsil": "59.4",
                    "slll": "0.122",
                    "slcly": "19.3",
                    "slcec": "-99",
                    "slcf": "0.0",
                    "sloc": "0.05",
                    "slmh": "C",
                    "slphw": "7.0",
                    "slsat": "0.439",
                    "sllb": "300"
                }
            ],
            "smhb": "IB001",
            "soil_lat": -34.1,
            "sltx": "71",
            "sl_source": "ALT"
        }
    ]
}