{
    "soils": [
        {
            "soil_id": "WI87688001",
            "sl_loc_3": "LMARTINETAS",
            "soil_long": -61.1,
            "smke": "IB001",
            "sldp": "-99",
            "classification": "Argiudol acuico",
            "sscol": "-99",
            "salb": "0.13",
            "sldr": "0.15",
            "slro": "76",
            "slpf": "1.00",
            "soil_name": "",
            "slnf": "0.40",
            "sl_loc_1": "ARGENTINA",
            "slu1": "18.5",
            "smpx": "IB001",
            "soilLayer": [
                {
                    "slrgf": "1.00",
                    "sldul": "0.314",
                    "slbdm": "1.04",
                    "slsil": "52.2",
                    "slll": "0.162",
                    "slcly": "28.4",
                    "slni": "-99",
                    "slcf": "00.0",
                    "sloc": "2.90",
                    "slmh": "A1",
                    "slphw": "6.3",
                    "slsat": "0.527",
                    "sllb": "021"
                },
                {
                    "slrgf": "0.33",
                    "sldul": "0.338",
                    "slbdm": "1.23",
                    "slsil": "49.9",
                    "slll": "0.200",
                    "slcly": "36.9",
                    "slni": "-99",
                    "slcf": "00.0",
                    "sloc": "0.90",
                    "slmh": "B1",
                    "slphw": "6.3",
                    "slsat": "0.460",
                    "sllb": "036"
                },
                {
                    "slrgf": "0.29",
                    "sldul": "0.354",
                    "slbdm": "1.25",
                    "slsil": "46.8",
                    "slll": "0.219",
                    "slcly": "41.2",
                    "slni": "-99",
                    "slcf": "00.0",
                    "sloc": "0.70",
                    "slmh": "B21T",
                    "slphw": "6.5",
                    "slsat": "0.451",
                    "sllb": "052"
                },
                {
                    "slrgf": "0.25",
                    "sldul": "0.347",
                    "slbdm": "1.27",
                    "slsil": "45.5",
                    "slll": "0.213",
                    "slcly": "39.9",
                    "slni": "-99",
                    "slcf": "00.0",
                    "sloc": "0.50",
                    "slmh": "B22T",
                    "slphw": "6.5",
                    "slsat": "0.447",
                    "sllb": "071"
                },
                {
                    "slrgf": "0.21",
                    "sldul": "0.337",
                    "slbdm": "1.28",
                    "slsil": "45.5",
                    "slll": "0.204",
                    "slcly": "37.9",
                    "slni": "-99",
                    "slcf": "00.0",
                    "sloc": "0.30",
                    "slmh": "B23T",
                    "slphw": "6.5",
                    "slsat": "0.443",
                    "sllb": "094"
                },
                {
                    "slrgf": "0.17",
                    "sldul": "0.328",
                    "slbdm": "1.31",
                    "slsil": "52.0",
                    "slll": "0.193",
                    "slcly": "35.4",
                    "slni": "-99",
                    "slcf": "00.0",
                    "sloc": "0.20",
                    "slmh": "B31",
                    "slphw": "6.5",
                    "slsat": "0.433",
                    "sllb": "100"
                }
            ],
            "smhb": "IB001",
            "soil_lat": -37.2,
            "sltx": "Aldecoa",
            "sl_source": "Estancia"
        }
    ]
}